Assignment-05/5.1/norgate.vhdl
-- from the ieee library we use std_logic_1164
-- defines a standard for logic values used in electronic design
-- for more info check the std_logic_1164.vhdl file in ghdl/libraries/ieee
-- ieee library also defines operators and keywords

-- wir verwenden std_logic_1164 aus der IEEE libary
-- diese Datei definiert die Standards fuer logische Werte im elektronischen Design
-- Details finden sich in der Datei std_logic_1164.vhdl in ghdl/libraries/ieee
-- Die IEEE libary definiert auch operatoren und Schluesselwoerter

library ieee;
use ieee.std_logic_1164.all;

-- entities defined in a file can be seen as black boxes
-- entities have ports that defines all inputs and outputs 
-- std_logic can have 9 different values, it is part of std_logic_1164 package
-- you can think of it as a single bit

-- die in einer Datei definierten entities koennen als black box angesehen werden. 
-- entities haben ports die Eingaben und Ausgaben definieren
-- std_logic kann 9 unterschiedliche Werte annehmen (siehe Aufgabe 2.1)
-- kann als einzelnes bit verstanden werden

entity norgate is
  -- the norgate as two in ports named "input1" and "input2", and one out port named "nor_result"
  -- das norgate hat zwei Eingangsports "input1" und "input2" sowie einen Ausgangsport "nor_result"
  
  port (
    input1 : in std_logic;
    input2 : in std_logic;
    nor_result : out std_logic
  );
end norgate;

-- architecture describes functionality of particular entity
-- like the implementation of a function
-- actually describes the "internal wiring" of block
-- interconnection signals, constants, or other components

-- die Architekture beschreibt die Funktionalitaet einer entity
-- aehnlich wie die Implementierung einer Funktion
-- beschreibt die "innere Verdrahtung" eines blocks
-- verbindet Signale, Konstanten oder andere Komponenten

architecture rtl of norgate is
  -- internal signal, not yet connected to the outside
  -- internes Signal, bisher nicht nach aussen verbunden
  signal nor_gate : std_logic;
  
begin
  -- setting the internal signal, based on the desired logical functionality (here: logical and of the two input values)
  -- internes Signal wird entsprechend der benoetigten Funktionalitaet gesetzt (hier: logisches und der Eingabewerte)

  nor_gate <= input1 nor input2;
  -- internal signal gets connected to the outside
  -- internes Signal wird nach aussen verbunden
  nor_result <= nor_gate;
end rtl;

Assignment-05/5.2/SR_Latch.vhdl
library ieee;
use ieee.std_logic_1164.all;

entity SR_Latch is
    port (
      S,R : in std_logic;
      Q,not_Q : out std_logic
    );
  end SR_Latch;

architecture Behavioral of SR_Latch is

    -- nor gate component from blatt 2
    component norgate is
        port (
            input1 : in std_logic;
            input2 : in std_logic;
            nor_result : out std_logic
        );
    end component;
    -- internal signals for feedback loop
    -- q and not_q are out ports so we cant read from them directly
    signal q_internal : std_logic;
    signal nq_internal : std_logic;
begin

    -- N1: inputs are S and q_internal (feedback from N2), output is nq_internal
    N1: norgate port map(input1 => S, input2 => q_internal, nor_result => nq_internal);
    -- N2: inputs are R and nq_internal (feedback from N1), output is q_internal
    N2: norgate port map(input1 => R, input2 => nq_internal, nor_result => q_internal);
    -- connect internal signals to output ports
    Q <= q_internal;
    not_Q <= nq_internal;

end Behavioral;

Assignment-05/5.1/andgate.vhdl
library ieee;
use ieee.std_logic_1164.all;
entity andgate is
  port (
    input1 : in std_logic;
    input2 : in std_logic;
    and_output : out std_logic
  );
end andgate;
architecture rtl of andgate is
  signal andgate_sig : std_logic;
begin
  andgate_sig <= input1 and input2;
  and_output <= andgate_sig;
end rtl;

Assignment-05/5.1/notgate.vhdl
library ieee;
use ieee.std_logic_1164.all;
entity notgate is
  port (
    input1 : in std_logic;
    not_output : out std_logic
  );
end notgate;
architecture rtl of notgate is
  signal notgate_sig : std_logic;
begin
  notgate_sig <= NOT input1;
  not_output <= notgate_sig;
end rtl;

Assignment-05/5.1/D_Latch.vhdl
library ieee;
use ieee.std_logic_1164.all;

entity D_Latch is
    port(
        D, clk : in std_logic;
        Q, not_Q : out std_logic
    );
end D_Latch;

architecture Behavioral of D_Latch is
    
    -- component declarations
    component SR_Latch is
        port(
            S, R : in std_logic;
            Q, not_Q : out std_logic
        );
    end component;
    component andgate is
        port(
            input1 : in std_logic;
            input2 : in std_logic;
            and_output : out std_logic
        );
    end component;
    component notgate is
        port(
            input1 : in std_logic;
            not_output : out std_logic
        );
    end component;
    -- internal signals
    signal S, R : std_logic;
    signal not_D : std_logic;
begin

    -- invert D
    not1: notgate port map(input1 => D, not_output => not_D);
    -- S = D AND CLK
    and1: andgate port map(input1 => D, input2 => clk, and_output => S);
    -- R = NT D AND CLK
    and2: andgate port map(input1 => not_D, input2 => clk, and_output => R);
    -- sr latch takes S and R and produces Q and not_Q
    sr1: SR_Latch port map(S => S, R => R, Q => Q, not_Q => not_Q);

end Behavioral;

Assignment-05/5.2/ps_ff.vhdl
library ieee;
use ieee.std_logic_1164.all;

entity ps_ff is
    port (
      d, clk: in std_logic;
      Q, not_Q : out std_logic
    );
  end ps_ff;

architecture behavioral of ps_ff is

    component D_Latch is
        port(
            D, clk : in std_logic;
            Q, not_Q : out std_logic
        );
    end component;
    component notgate is
        port(
            input1 : in std_logic;
            not_output : out std_logic
        );
    end component;
    -- invertiertes taktsignal fuer primary latch
    signal not_clk : std_logic;
    -- verbindung zwischen primary und secondary latch
    signal n1, not_n1 : std_logic;
begin

    -- takt invertieren
    not1: notgate port map(input1 => clk, not_output => not_clk);
    -- primary latch bekommt invertierten takt
    L1: D_Latch port map(D => d, clk => not_clk, Q => n1, not_Q => not_n1);
    -- secondary latch bekommt normalen takt
    L2: D_Latch port map(D => n1, clk => clk, Q => Q, not_Q => not_Q);
end behavioral ;

Assignment-05/5.2/ps_ff_rst.vhdl
library ieee;
use ieee.std_logic_1164.all;
-- d flip flop mit synchronem reset
-- new_d = d and not rst
-- bei aufsteigender taktflanke: wenn rst=1 wird q=0, sonst q=d
entity ps_ff_rst is
    port (
        d, clk, rst : in std_logic;
        Q, not_Q : out std_logic
    );
end ps_ff_rst;
architecture behavioral of ps_ff_rst is
    component ps_ff is
        port(
            d, clk : in std_logic;
            Q, not_Q : out std_logic
        );
    end component;
    component notgate is
        port(
            input1 : in std_logic;
            not_output : out std_logic
        );
    end component;
    component andgate is
        port(
            input1 : in std_logic;
            input2 : in std_logic;
            and_output : out std_logic
        );
    end component;
    -- not rst signal
    signal not_rst : std_logic;
    -- new d after reset logic
    signal new_d : std_logic;
begin
    -- rst invertieren
    not1: notgate port map(input1 => rst, not_output => not_rst);
    -- new_d = d and not_rst
    and1: andgate port map(input1 => d, input2 => not_rst, and_output => new_d);
    -- flip flop bekommt new_d statt d
    ff1: ps_ff port map(d => new_d, clk => clk, Q => Q, not_Q => not_Q);
end behavioral;

Assignment-05/5.2/ps_ff_rst_tb.vhdl
library ieee;
use ieee.std_logic_1164.all;
entity ps_ff_rst_tb is
end ps_ff_rst_tb;
architecture testbench of ps_ff_rst_tb is
    component ps_ff_rst
        port (
            d, clk, rst : in std_logic;
            Q, not_Q : out std_logic
        );
    end component;
    signal d, clk, rst : std_logic;
    signal Q, not_Q : std_logic;
begin
    ff_inst: ps_ff_rst port map(d => d, clk => clk, rst => rst, Q => Q, not_Q => not_Q);
    process begin
        -- clk=0, d=0, rst=0 -> memory
        clk <= '0'; d <= '0'; rst <= '0'; wait for 10 ns;
        -- clk=0, d=1, rst=0 -> memory
        clk <= '0'; d <= '1'; rst <= '0'; wait for 10 ns;
        -- rising edge, d=1, rst=0 -> Q becomes 1
        clk <= '1'; d <= '1'; rst <= '0'; wait for 10 ns;
        -- clk=1, d=0, rst=0 -> Q stays 1
        clk <= '1'; d <= '0'; rst <= '0'; wait for 10 ns;
        -- falling edge
        clk <= '0'; d <= '0'; rst <= '0'; wait for 10 ns;
        -- rising edge, d=0, rst=0 -> Q becomes 0
        clk <= '1'; d <= '0'; rst <= '0'; wait for 10 ns;
        -- set Q to 1 again
        clk <= '0'; d <= '1'; rst <= '0'; wait for 10 ns;
        clk <= '1'; d <= '1'; rst <= '0'; wait for 10 ns;
        -- synchronous reset: rst=1, rising edge -> Q becomes 0
        clk <= '0'; d <= '1'; rst <= '1'; wait for 10 ns;
        clk <= '1'; d <= '1'; rst <= '1'; wait for 10 ns;
        assert false report "End of test";
        wait;
    end process;
end testbench;

Assignment-05/5.2/testbench.vcd
$date
  Fri May 29 13:17:14 2026
$end
$version
  GHDL v0
$end
$timescale
  1 fs
$end
$scope module standard $end
$upscope $end
$scope module std_logic_1164 $end
$upscope $end
$scope module ps_ff_rst_tb $end
$var reg 1 ! d $end
$var reg 1 " clk $end
$var reg 1 # rst $end
$var reg 1 $ q $end
$var reg 1 % not_q $end
$scope module ff_inst $end
$var reg 1 & d $end
$var reg 1 ' clk $end
$var reg 1 ( rst $end
$var reg 1 ) q $end
$var reg 1 * not_q $end
$var reg 1 + not_rst $end
$var reg 1 , new_d $end
$scope module not1 $end
$var reg 1 - input1 $end
$var reg 1 . not_output $end
$var reg 1 / notgate_sig $end
$upscope $end
$scope module and1 $end
$var reg 1 0 input1 $end
$var reg 1 1 input2 $end
$var reg 1 2 and_output $end
$var reg 1 3 andgate_sig $end
$upscope $end
$scope module ff1 $end
$var reg 1 4 d $end
$var reg 1 5 clk $end
$var reg 1 6 q $end
$var reg 1 7 not_q $end
$var reg 1 8 not_clk $end
$var reg 1 9 n1 $end
$var reg 1 : not_n1 $end
$scope module not1 $end
$var reg 1 ; input1 $end
$var reg 1 < not_output $end
$var reg 1 = notgate_sig $end
$upscope $end
$scope module l1 $end
$var reg 1 > d $end
$var reg 1 ? clk $end
$var reg 1 @ q $end
$var reg 1 A not_q $end
$var reg 1 B s $end
$var reg 1 C r $end
$var reg 1 D not_d $end
$scope module not1 $end
$var reg 1 E input1 $end
$var reg 1 F not_output $end
$var reg 1 G notgate_sig $end
$upscope $end
$scope module and1 $end
$var reg 1 H input1 $end
$var reg 1 I input2 $end
$var reg 1 J and_output $end
$var reg 1 K andgate_sig $end
$upscope $end
$scope module and2 $end
$var reg 1 L input1 $end
$var reg 1 M input2 $end
$var reg 1 N and_output $end
$var reg 1 O andgate_sig $end
$upscope $end
$scope module sr1 $end
$var reg 1 P s $end
$var reg 1 Q r $end
$var reg 1 R q $end
$var reg 1 S not_q $end
$var reg 1 T q_internal $end
$var reg 1 U nq_internal $end
$scope module n1 $end
$var reg 1 V input1 $end
$var reg 1 W input2 $end
$var reg 1 X nor_result $end
$var reg 1 Y nor_gate $end
$upscope $end
$scope module n2 $end
$var reg 1 Z input1 $end
$var reg 1 [ input2 $end
$var reg 1 \ nor_result $end
$var reg 1 ] nor_gate $end
$upscope $end
$upscope $end
$upscope $end
$scope module l2 $end
$var reg 1 ^ d $end
$var reg 1 _ clk $end
$var reg 1 ` q $end
$var reg 1 a not_q $end
$var reg 1 b s $end
$var reg 1 c r $end
$var reg 1 d not_d $end
$scope module not1 $end
$var reg 1 e input1 $end
$var reg 1 f not_output $end
$var reg 1 g notgate_sig $end
$upscope $end
$scope module and1 $end
$var reg 1 h input1 $end
$var reg 1 i input2 $end
$var reg 1 j and_output $end
$var reg 1 k andgate_sig $end
$upscope $end
$scope module and2 $end
$var reg 1 l input1 $end
$var reg 1 m input2 $end
$var reg 1 n and_output $end
$var reg 1 o andgate_sig $end
$upscope $end
$scope module sr1 $end
$var reg 1 p s $end
$var reg 1 q r $end
$var reg 1 r q $end
$var reg 1 s not_q $end
$var reg 1 t q_internal $end
$var reg 1 u nq_internal $end
$scope module n1 $end
$var reg 1 v input1 $end
$var reg 1 w input2 $end
$var reg 1 x nor_result $end
$var reg 1 y nor_gate $end
$upscope $end
$scope module n2 $end
$var reg 1 z input1 $end
$var reg 1 { input2 $end
$var reg 1 | nor_result $end
$var reg 1 } nor_gate $end
$upscope $end
$upscope $end
$upscope $end
$upscope $end
$upscope $end
$upscope $end
$enddefinitions $end
#0
0!
0"
0#
U$
U%
0&
0'
0(
U)
U*
1+
0,
0-
1.
1/
00
11
02
03
04
05
U6
U7
18
09
1:
0;
1<
1=
0>
1?
0@
1A
0B
1C
1D
0E
1F
1G
0H
1I
0J
0K
1L
1M
1N
1O
0P
1Q
0R
1S
0T
1U
0V
0W
1X
1Y
1Z
1[
0\
0]
0^
0_
U`
Ua
0b
0c
1d
0e
1f
1g
0h
0i
0j
0k
1l
0m
0n
0o
0p
0q
Ur
Us
Ut
Uu
0v
Uw
Ux
Uy
0z
U{
U|
U}
#10000000
1!
1&
1,
10
12
13
14
19
0:
1>
1@
0A
1B
0C
0D
1E
0F
0G
1H
1J
1K
0L
0N
0O
1P
0Q
1R
0S
1T
0U
1V
1W
0X
0Y
0Z
0[
1\
1]
1^
0d
1e
0f
0g
1h
0l
#20000000
1"
1$
0%
1'
1)
0*
15
16
07
08
1;
0<
0=
0?
0B
0I
0J
0K
0M
0P
0V
1_
1`
0a
1b
1i
1j
1k
1m
1p
1r
0s
1t
0u
1v
1w
0x
0y
0{
1|
1}
#30000000
0!
0&
0,
00
02
03
04
0>
1D
0E
1F
1G
0H
1L
#40000000
0"
0'
05
18
09
1:
0;
1<
1=
1?
0@
1A
1C
1I
1M
1N
1O
1Q
0R
1S
0T
1U
0W
1X
1Y
1Z
1[
0\
0]
0^
0_
0b
1d
0e
1f
1g
0h
0i
0j
0k
1l
0m
0p
0v
#50000000
1"
0$
1%
1'
0)
1*
15
06
17
08
1;
0<
0=
0?
0C
0I
0M
0N
0O
0Q
0Z
1_
0`
1a
1c
1i
1m
1n
1o
1q
0r
1s
0t
1u
0w
1x
1y
1z
1{
0|
0}
#60000000
1!
0"
1&
0'
1,
10
12
13
14
05
18
19
0:
0;
1<
1=
1>
1?
1@
0A
1B
0C
0D
1E
0F
0G
1H
1I
1J
1K
0L
1M
0N
0O
1P
0Q
1R
0S
1T
0U
1V
1W
0X
0Y
0Z
0[
1\
1]
1^
0_
0c
0d
1e
0f
0g
1h
0i
0l
0m
0n
0o
0q
0z
#70000000
1"
1$
0%
1'
1)
0*
15
16
07
08
1;
0<
0=
0?
0B
0I
0J
0K
0M
0P
0V
1_
1`
0a
1b
1i
1j
1k
1m
1p
1r
0s
1t
0u
1v
1w
0x
0y
0{
1|
1}
#80000000
0"
1#
0'
1(
0+
0,
1-
0.
0/
01
02
03
04
05
18
09
1:
0;
1<
1=
0>
1?
0@
1A
0B
1C
1D
0E
1F
1G
0H
1I
0J
0K
1L
1M
1N
1O
0P
1Q
0R
1S
0T
1U
0V
0W
1X
1Y
1Z
1[
0\
0]
0^
0_
0b
1d
0e
1f
1g
0h
0i
0j
0k
1l
0m
0p
0v
#90000000
1"
0$
1%
1'
0)
1*
15
06
17
08
1;
0<
0=
0?
0C
0I
0M
0N
0O
0Q
0Z
1_
0`
1a
1c
1i
1m
1n
1o
1q
0r
1s
0t
1u
0w
1x
1y
1z
1{
0|
0}
